libqc/__init__.py
libqc/counts.py
libqc/library.py
libqc/lib/brunello.csv
libqc/lib/brunello.fa
libqc-0.0.8.dist-info/METADATA
libqc-0.0.8.dist-info/WHEEL
libqc-0.0.8.dist-info/top_level.txt
libqc-0.0.8.dist-info/RECORD
