Metadata-Version: 2.1
Name: libqc
Version: 0.0.8
Summary: sgRNA Library QC
Home-page: UNKNOWN
Author-email: kenny@latch.bio
License: UNKNOWN
Platform: UNKNOWN
